boost_py/__init__.py
boost_py/boost_object.py
boost_py/common_utils.py
boost_py/datetime_utils.py
boost_py-0.0.1.dist-info/DESCRIPTION.rst
boost_py-0.0.1.dist-info/METADATA
boost_py-0.0.1.dist-info/RECORD
boost_py-0.0.1.dist-info/WHEEL
boost_py-0.0.1.dist-info/entry_points.txt
boost_py-0.0.1.dist-info/metadata.json
boost_py-0.0.1.dist-info/top_level.txt
