Metadata-Version: 2.0
Name: boost-py
Version: 0.0.1
Summary: boost-py is for python script&service&spider and so on development quickly
Home-page: https://github.com/yeexiao/boost-py
Author: guu
Author-email: yeexiao@yeah.net
License: MIT
Keywords: python project quick start
Platform: UNKNOWN
Classifier: Development Status :: 3 - Alpha
Classifier: Intended Audience :: Developers
Classifier: Topic :: Software Development :: Build Tools
Classifier: License :: OSI Approved :: MIT License
Classifier: Programming Language :: Python :: 3
Classifier: Programming Language :: Python :: 3.3
Classifier: Programming Language :: Python :: 3.4
Classifier: Programming Language :: Python :: 3.5
Requires-Python: >=3
Requires-Dist: peppercorn
Provides-Extra: dev
Requires-Dist: check-manifest; extra == 'dev'
Provides-Extra: test
Requires-Dist: coverage; extra == 'test'
